ChangeLog
LICENSE.txt
MANIFEST.in
Makefile
README.md
celstash.py
requirements.txt
run-tests.sh
setup.py
test-requirements.txt
test_celstash.py
celstash.egg-info/PKG-INFO
celstash.egg-info/SOURCES.txt
celstash.egg-info/dependency_links.txt
celstash.egg-info/requires.txt
celstash.egg-info/top_level.txt