Metadata-Version: 1.1
Name: celstash
Version: 0.1.0
Summary: log from celery to logstash and structured log
Home-page: https://github.com/CyberInt/celstash
Author: CyberInt
Author-email: tools@cyberint.com
License: MIT
Platform: UNKNOWN
Classifier: Development Status :: 4 - Beta
Classifier: Intended Audience :: Developers
Classifier: License :: OSI Approved :: MIT License
Classifier: Programming Language :: Python
Classifier: Programming Language :: Python :: 2
Classifier: Topic :: Software Development :: Libraries
Classifier: Topic :: Software Development :: Libraries :: Python Modules
